foxapi/__init__.py
foxapi/foxapi.py
foxapi/utils.py
foxapi/Images/MapIcons/10.png
foxapi/Images/MapIcons/11.png
foxapi/Images/MapIcons/12.png
foxapi/Images/MapIcons/13.png
foxapi/Images/MapIcons/14.png
foxapi/Images/MapIcons/15.png
foxapi/Images/MapIcons/16.png
foxapi/Images/MapIcons/17.png
foxapi/Images/MapIcons/18.png
foxapi/Images/MapIcons/19.png
foxapi/Images/MapIcons/20.png
foxapi/Images/MapIcons/21.png
foxapi/Images/MapIcons/22.png
foxapi/Images/MapIcons/23.png
foxapi/Images/MapIcons/27.png
foxapi/Images/MapIcons/28.png
foxapi/Images/MapIcons/29.png
foxapi/Images/MapIcons/30.png
foxapi/Images/MapIcons/32.png
foxapi/Images/MapIcons/33.png
foxapi/Images/MapIcons/34.png
foxapi/Images/MapIcons/35.png
foxapi/Images/MapIcons/37.png
foxapi/Images/MapIcons/38.png
foxapi/Images/MapIcons/39.png
foxapi/Images/MapIcons/40.png
foxapi/Images/MapIcons/41.png
foxapi/Images/MapIcons/45.png
foxapi/Images/MapIcons/46.png
foxapi/Images/MapIcons/47.png
foxapi/Images/MapIcons/5.png
foxapi/Images/MapIcons/51.png
foxapi/Images/MapIcons/52.png
foxapi/Images/MapIcons/53.png
foxapi/Images/MapIcons/54.png
foxapi/Images/MapIcons/56.png
foxapi/Images/MapIcons/57.png
foxapi/Images/MapIcons/58.png
foxapi/Images/MapIcons/59.png
foxapi/Images/MapIcons/6.png
foxapi/Images/MapIcons/60.png
foxapi/Images/MapIcons/61.png
foxapi/Images/MapIcons/62.png
foxapi/Images/MapIcons/7.png
foxapi/Images/MapIcons/70.png
foxapi/Images/MapIcons/71.png
foxapi/Images/MapIcons/72.png
foxapi/Images/MapIcons/75.png
foxapi/Images/MapIcons/8.png
foxapi/Images/MapIcons/83.png
foxapi/Images/MapIcons/84.png
foxapi/Images/MapIcons/9.png
foxapi/Images/MapIcons/DebugIcon.png
foxapi/Images/MapIcons/MapIconCivicCenter.png
foxapi/Images/MapIcons/MapIconFortCursed.png
foxapi/Images/MapIcons/MapIconForwardBase1.png
foxapi/Images/MapIcons/MapIconScorchedTown.png
foxapi/Images/MapIcons/MapIconTownHall.png
foxapi/Images/MapIcons/MapIconVictory.png
foxapi/Images/MapsHex/MapAcrithiaHex.png
foxapi/Images/MapsHex/MapAllodsBightHex.png
foxapi-1.7.2.dist-info/licenses/LICENSE
foxapi-1.7.2.dist-info/METADATA
foxapi-1.7.2.dist-info/WHEEL
foxapi-1.7.2.dist-info/top_level.txt
foxapi-1.7.2.dist-info/RECORD
