Metadata-Version: 2.4
Name: foxapi
Version: 1.7.2
Summary: A wrapper for the foxhole API
Home-page: https://github.com/ThePhoenix78/FoxAPI
Download-URL: https://github.com/ThePhoenix78/FoxAPI/tarball/master
Author: ThePhoenix78
Author-email: thephoenix788@gmail.com
License: MIT
Keywords: foxhole,foxapi,foxhole-game,foxhole-api
Classifier: Programming Language :: Python :: 3
Classifier: License :: OSI Approved :: MIT License
Classifier: Operating System :: OS Independent
License-File: LICENSE
Requires-Dist: requests
Requires-Dist: pillow
Requires-Dist: aiohttp
Dynamic: author
Dynamic: author-email
Dynamic: classifier
Dynamic: description
Dynamic: description-content-type
Dynamic: download-url
Dynamic: home-page
Dynamic: keywords
Dynamic: license
Dynamic: license-file
Dynamic: requires-dist
Dynamic: summary
